license.txt
setup.cfg
setup.py
src/openapi3_parser_x.egg-info/PKG-INFO
src/openapi3_parser_x.egg-info/SOURCES.txt
src/openapi3_parser_x.egg-info/dependency_links.txt
src/openapi3_parser_x.egg-info/requires.txt
src/openapi3_parser_x.egg-info/top_level.txt
src/openapi_parser/__init__.py
src/openapi_parser/enumeration.py
src/openapi_parser/errors.py
src/openapi_parser/loose_types.py
src/openapi_parser/parser.py
src/openapi_parser/py.typed
src/openapi_parser/resolver.py
src/openapi_parser/specification.py
src/openapi_parser/builders/__init__.py
src/openapi_parser/builders/common.py
src/openapi_parser/builders/content.py
src/openapi_parser/builders/external_doc.py
src/openapi_parser/builders/header.py
src/openapi_parser/builders/info.py
src/openapi_parser/builders/oauth_flow.py
src/openapi_parser/builders/operation.py
src/openapi_parser/builders/parameter.py
src/openapi_parser/builders/path.py
src/openapi_parser/builders/request.py
src/openapi_parser/builders/response.py
src/openapi_parser/builders/schema.py
src/openapi_parser/builders/schemas.py
src/openapi_parser/builders/security.py
src/openapi_parser/builders/server.py
src/openapi_parser/builders/tag.py