Metadata-Version: 2.1
Name: openapi3-parser-x
Version: 1.1.22
Summary: OpenAPI v3 parser
Home-page: https://github.com/MrAdhit/openapi3-parser
Author: MrAdhit
Author-email: mradhit@kingland.id
License: MIT
Project-URL: Source, https://github.com/MrAdhit/openapi3-parser
Keywords: swagger,python,swagger-parser,openapi3-parser-x,parser,openapi3,swagger-api
Classifier: Development Status :: 4 - Beta
Classifier: License :: OSI Approved :: MIT License
Classifier: Operating System :: OS Independent
Classifier: Intended Audience :: Developers
Classifier: Programming Language :: Python :: 3.9
Classifier: Topic :: Software Development :: Libraries
License-File: license.txt
